mcasm/__main__.py
mcasm/version.py
mcasm/py.typed
mcasm/_core.cpython-38-x86_64-linux-gnu.so
mcasm/__init__.py
mcasm/_core/__init__.pyi
mcasm/_core/mc/__init__.pyi
mcasm-0.4.0.dist-info/RECORD
mcasm-0.4.0.dist-info/METADATA
mcasm-0.4.0.dist-info/LICENSE.txt
mcasm-0.4.0.dist-info/WHEEL
mcasm-0.4.0.dist-info/top_level.txt
