Metadata-Version: 2.1
Name: mcasm
Version: 0.4.0
Summary: Assemble code to bytes using LLVM's MC layer
Home-page: https://github.com/grammatech/mc-asm
Author: GrammaTech, Inc.
Author-email: gtirb@grammatech.com
License: MIT
Classifier: Intended Audience :: Developers
Classifier: Programming Language :: Python :: 3
Requires-Python: >=3.7
License-File: LICENSE.txt
Provides-Extra: cli
Requires-Dist: rich~=12.0; extra == "cli"
Provides-Extra: test
Requires-Dist: pytest; extra == "test"
